niflow_manager/__init__.py
niflow_manager/_version.py
niflow_manager/cli/__init__.py
niflow_manager/cli/build.py
niflow_manager/cli/init.py
niflow_manager/cli/install.py
niflow_manager/cli/main.py
niflow_manager/cli/test.py
niflow_manager/cli/tests/__init__.py
niflow_manager/cli/tests/test_init.py
niflow_manager/cli/tests/test_main.py
niflow_manager/data/templates/base/README.md
niflow_manager/data/templates/base/spec.yml
niflow_manager/data/templates/base/doc/README.md
niflow_manager/data/templates/base/test/README.md
niflow_manager/data/templates/base/test/data/README.md
niflow_manager/data/templates/base/test/scripts/README.md
niflow_manager/data/templates/python/package/setup.cfg
niflow_manager/data/templates/python/package/setup.py
niflow_manager/data/templates/python/package/niflow/__init__.py
niflow_manager/data/templates/python/package/niflow/{ORGANIZATION}/__init__.py
niflow_manager/data/templates/python/package/niflow/{ORGANIZATION}/{WORKFLOW}/__init__.py
niflow_manager/data/templates/python/package/niflow/{ORGANIZATION}/{WORKFLOW}/cli.py
niflow_manager/data/templates/python/package/niflow/{ORGANIZATION}/{WORKFLOW}/workflow.py
niflow_manager/data/templates/python-bidsapp-1.0/package/setup.cfg
niflow_manager/data/templates/python-bidsapp-1.0/package/{ORGANIZATION}/{WORKFLOW}/cli.py
niflow_manager/data/templates/python-bidsapp-1.0/package/{ORGANIZATION}/{WORKFLOW}/workflow.py
niflow_manager/util/__init__.py
niflow_manager/util/fsutil.py
niflow_manager/util/git.py
niflow_manager/util/tests/__init__.py
niflow_manager/util/tests/test_git.py
niflow_manager-0.0.3.dist-info/LICENSE
niflow_manager-0.0.3.dist-info/METADATA
niflow_manager-0.0.3.dist-info/WHEEL
niflow_manager-0.0.3.dist-info/entry_points.txt
niflow_manager-0.0.3.dist-info/top_level.txt
niflow_manager-0.0.3.dist-info/RECORD
